Workbook
Name Slicer_outletType: #N/A
Name Slicer_salesChannel: #N/A
Name Slicer_state: #N/A

Sheet Details
B1: Orders - July, 2021
B3: Fields | C3: Definitions | L3: Guide
B4: OrderedAt Date | C4: The Order Date | L4: All Analyses should be done USD
B5: Customer Name | C5: Name Of The Retail Outlet | J5: Exchange Rate | L5: ZAR | M5: 14.72
B6: outletType | C6: Classification of the Retail Outlet | L6: NGN | M6: 402
B7: Producer | C7: The Line Item Producer
B8: Product | C8: The Line Item Product
B9: Category Group | C9: The Broad Category of the Line Item
B10: Quantity | C10: The Quantity Of The Line Item (SKU)
B11: Unit Price | C11: The Unit Price Of The Line Item (SKU)
B12: shippingStatus | C12: The Fulfilment Status Of The Line Item (SKU)
B13: Delivery Agent | C13: The Delivery Agent The Order Was Assigned To
B14: State | C14: The State where the retailer's store is Located
B15: Country | C15: The Country Where The retailers store is Located
B16: Currency | C16: The Currency The Order Is Denominated In
B17: saleschannel | C17: The Channel The Order Was Raised Through

Sheet Sheet4
A1: Row Labels | B1: Count of unique outlet type
A2: Convenience Store | B2: 700
A3: Kiosk | B3: 698
A4: Supermarket | B4: 674
A5: Grand Total | B5: 2072
A8: Row Labels
A9: NG
A10: ZA
A11: Grand Total
A13: Row Labels | B13: Count of shippingStatus2
A14: cancelled | B14: 947
A15: delivered | B15: 7957
A16: Grand Total | B16: 8904

Sheet Sheet9
A3: Row Labels | B3: Average of Fulfilment time
A4: cancelled | B4: 1.9949233
A5: delivered | B5: 1.6702273
A6: Grand Total | B6: 1.7047609

Sheet Sheet10
A3: Row Labels
A4: cancelled
A5: delivered
A6: Grand Total

Sheet Sheet12
A3: Row Labels | B3: Count of Product Variant
A4: Convenience Store | B4: 86
A5: Kiosk | B5: 90
A6: Supermarket | B6: 88
A7: Grand Total | B7: 264

Sheet Sheet2
A3: Row Labels
A4: 00
A5: 01
A6: 02
A7: 03
A8: 04
A9: 05
A10: 06
A11: 07
A12: 08
A13: 09
A14: 10
... A28: Grand Total

Sheet Sheet3
A3: Row Labels | B3: Average of Quantity
A4: Danone Nigeria | B4: 1.3282443
A5: Unilever SA | B5: 1.663451
A6: PZ Cussons Nigeria Plc | B6: 2.1530945
A7: Hayat Kimya Nigeria Limited | B7: 2.271777
A8: Nourdm Global | B8: 3.2
A9: Extreme Manufacturing Nig Ltd | B9: 3.875817
A10: Nasco | B10: 5.6882353
A11: Arla Foods | B11: 6.028599
A12: Unilever Nigeria Plc | B12: 7.095679
A13: DUFIL Prima foods Plc | B13: 8.0597738
A14: Chi Nigeria Limited | B14: 8.3952641
A15: Guinness Nigeria Plc | B15: 12.416268
... A17: Grand Total | B17: 4.1458895
A19: Row Labels
A20: Arla Foods
A21: Chi Nigeria Limited
A22: Danone Nigeria
A23: DUFIL Prima foods Plc
A24: Extreme Manufacturing Nig Ltd
A25: Flour Mills of Nigeria
A26: Guinness Nigeria Plc
A27: Hayat Kimya Nigeria Limited
A28: Nasco
A29: Nourdm Global
A30: PZ Cussons Nigeria Plc
... A33: Grand Total
A35: Count of Quantity | B35: Column Labels
A36: Row Labels | B36: Field Sales | C36: Mobile App | D36: Telesales | E36: Grand Total
A37: Indomie Indomitable Pack | B37: 56 | C37: 29 | D37: 160 | E37: 245
A38: Sunlight Dishwashing Liquid | C38: 196 | D38: 56 | E38: 252
A39: Surf Detergent | C39: 245 | D39: 55 | E39: 300
A40: So Easy | B40: 57 | C40: 41 | D40: 207 | E40: 305
A41: Robertsons Spices | C41: 275 | D41: 65 | E41: 340
A42: Hollandia Evap. Milk | B42: 109 | C42: 30 | D42: 231 | E42: 370
A43: OMO | C43: 364 | D43: 114 | E43: 478
A44: Dano Cool Cow | B44: 260 | C44: 47 | D44: 368 | E44: 675
A45: Knorr Soups | C45: 675 | D45: 167 | E45: 842
A46: Sunlight Laundry Detergent | C46: 722 | D46: 212 | E46: 934
A47: Grand Total | B47: 482 | C47: 2624 | D47: 1635 | E47: 4741

Sheet Sheet11
A3: Row Labels | B3: Count of Order No.
A4: 10 | B4: 1062
A5: 11 | B5: 1112
A6: 12 | B6: 977
A7: Grand Total | B7: 3151
N11: 16.22
A19: Row Labels | B19: Average of Fulfilment time
A20: Anambra | B20: 0.68194444
A21: Kano | B21: 0.69340278
A22: Oyo | B22: 0.76203704
A23: Lagos | B23: 1.4258169
A24: Ogun | B24: 1.4715278
A25: FCT | B25: 1.529343
A26: Abia | B26: 1.7173611
A27: Gauteng | B27: 1.9604135
A28: Soweto | B28: 2.25
A29: Katlehong | B29: 3
A30: Rivers | B30: 4.3068056
A31: Grand Total | B31: 1.7047609
G72: Row Labels | H72: Average fulfilment time
G73: Anambra | H73: 16.22
G74: Kano | H74: 16.38
G75: Oyo | H75: 18.17
G76: Lagos | H76: 10.13
G77: Ogun | H77: 11.19
G78: FCT | H78: 12.42
G79: Abia | H79: 17.13
G80: Gauteng | H80: 23.03
G81: Soweto | H81: 6
G82: Katlehong | H82: 0
G83: Rivers | H83: 7.21

Sheet Sheet16
A3: Row Labels | B3: Count of Order No. | C3: Average of Fulfilment time
A4: cancelled | B4: 947 | C4: 1.9949233
A5: delivered | B5: 7957 | C5: 1.6702273

Sheet Sheet15
B3: Column Labels
A4: Row Labels | B4: cancelled | C4: delivered
A5: Adeleye Dayo
A6: Agbanije Babatunde Gabriel
A7: Dayo Oludaisi
A8: Ismael Ishmael
A9: Kagiso Katlego
A10: Kayode Taiwo
A11: Nomfundo Sibongile
A12: Olugbenga Oginni
A13: Omosanya Olubukola Okeade
A14: Onasanya Adetola
A15: Samuel Shola

Sheet Sheet8
A3: Row Labels | B3: Count of Late/early delivery
A4: early | B4: 0.34737197
A5: late | B5: 0.65262803
A6: Grand Total | B6: 1

Sheet Sheet13
A3: Count of OrderAt Date | D3: Row Labels | E3: Count of OrderAt Date
A4: 8904 | D4: Fabric Clean | E4: 2495
D5: Spices | E5: 1643
D6: Processed Food | E6: 863
D7: Toileteries | E7: 859
D8: Milk | E8: 778
D9: Yoghurt | E9: 759
D10: Household Clean | E10: 340
D11: Infant Care | E11: 281
D12: Coffee / Tea | E12: 270
D13: Cereal | E13: 166
D14: Culinary | E14: 103
D15: Bitters | E15: 65
D16: Beer | E16: 63
... D27: CSD | E27: 1

Sheet Sheet14
A1: salesChannel | B1: (All)
A2: state | B2: (All)
A3: outletType | B3: (All)
A5: Column Labels
A6: Knorr Seasoning | B6: Sunlight Laundry Detergent | C6: Grand Total

Sheet Sheet17

Sheet Sheet18
B3: Column Labels
A4: Row Labels | B4: cancelled | C4: delivered | D4: Grand Total
A5: 00
A6: 01
A7: 02
A8: 03
A9: 04
A10: 05
A11: 06
A12: 07
A13: 08
A14: 09
A15: 10
A16: 11
... A29: Grand Total

Sheet Sheet19
A3: Row Labels
A4: Abdulahi Shehu
A5: Abdullahi Sule
A6: Adeleye Dayo
A7: Adeniyi Rahman
A8: Adetoro Oluranti
A9: Adetunji Adepoju
A10: Adewale Mustapha
A11: Agbanije Babatunde Gabriel
A12: Agenu Chukwudi
A13: Ajie Chukwumela
A14: Akinwande Akinbiyi
... A101: Grand Total

Sheet Sheet20
A3: Row Labels
A4: cancelled
A5: delivered
A6: Grand Total

Sheet Sheet21
B3: Column Labels | H3: Count of Order No. | I3: Column Labels
A4: Row Labels | B4: cancelled | C4: delivered | D4: Grand Total | H4: Row Labels | I4: cancelled | J4: delivered | K4: Grand Total
A5: Axe Deodorant | H5: Fandango | I5: 1 | J5: 0 | K5: 1
A6: Baileys Irish Cream | H6: Fan Vanille | I6: 0.5 | J6: 0.5 | K6: 1
A7: Blue Band | H7: Golden Penny Flour | I7: 0.5 | J7: 0.5 | K7: 1
A8: Brut Roll On | H8: POND`S Face Care | I8: 0.4 | J8: 0.6 | K8: 1
A9: Canoe Bar Soap | H9: Sunlight Bath Soap | I9: 0.28571429 | J9: 0.71428571 | K9: 1
A10: Caprisonne | H10: Knorrox Mince | I10: 0.25 | J10: 0.75 | K10: 1
A11: Chivita Active | H11: Handy Andy Cleaning Cream | I11: 0.23913043 | J11: 0.76086957 | K11: 1
A12: Chivita Exotic | H12: Surf Cleaner | I12: 0.22222222 | J12: 0.77777778 | K12: 1
A13: Chivita Premium | H13: Domestos Toilet Cleaner | I13: 0.21428571 | J13: 0.78571429 | K13: 1
A14: Close up | H14: Surf Dishwashing Liquid | I14: 0.2 | J14: 0.8 | K14: 1
A15: Close Up | H15: Molped Sanitary Towel | I15: 0.2 | J15: 0.8 | K15: 1
A16: Dano Cool Cow | H16: Shield Deodorant | I16: 0.1875 | J16: 0.8125 | K16: 1
... A93: Grand Total | H93: Close up | I93: 0 | J93: 1 | K93: 1

Sheet Sheet22
A3: Row Labels
A4: 2 Brothers Supermaket
A5: 2 Cees Supermarket
A6: 2020Soliana
A7: 234 Store
A8: 234Store
A9: 3 Brothers Supermarket
A10: 3 Star Mini Market
A11: 422 Tuck Shop
A12: A 2 Z Store
A13: A C Mark Ventures
A14: A Line Shop 1
... A2076: Grand Total

Sheet Orders - July, 2021
A1: OrderAt Date | B1: customer Name | C1: outletType | D1: Producer | E1: Product | F1: Category Group | G1: Quantity | H1: Unit Price | I1: shippingStatus | J1: Delivery Agent | K1: state | L1: country | M1: currency | N1: salesChannel | O1: Sales
A2: 44378.062 | B2: Mummy Marvelous Store | C2: Supermarket | D2: Chi Nigeria Limited | E2: Hollandia Evap. Milk | F2: Breakfast & Snacks | G2: 2 | H2: 3200 | I2: delivered | J2: Kayode Oluwashina | K2: Lagos | L2: NG | M2: NGN | N2: Telesales | O2: =IF(Orders[[#This Row],[currency]]="NGN", (Orders[[#This Row],[Unit Price]]*Orders[[#This Row],[Quantity]]/Details!$M$6), (Orders[[#This Row],[Unit Price]]*Orders[[#This Row],[Quantity]]/Details!$M$5)) -> 15.920398
A3: 44378.062 | B3: Mummy Marvelous Store | C3: Supermarket | D3: Unilever Nigeria Plc | E3: Lipton Special | F3: Breakfast & Snacks | G3: 2 | H3: 3500 | I3: cancelled | J3: Edem Ebia | K3: Lagos | L3: NG | M3: NGN | N3: Telesales | O3: =IF(Orders[[#This Row],[currency]]="NGN", (Orders[[#This Row],[Unit Price]]*Orders[[#This Row],[Quantity]]/Details!$M$6), (Orders[[#This Row],[Unit Price]]*Orders[[#This Row],[Quantity]]/Details!$M$5)) -> 17.412935
A4: 44378.081 | B4: Facodon | C4: Convenience Store | D4: DUFIL Prima foods Plc | E4: Indomie Indomitable Pack | F4: Food | G4: 5 | H4: 2400 | I4: delivered | J4: Edem Ebia | K4: Lagos | L4: NG | M4: NGN | N4: Telesales | O4: =IF(Orders[[#This Row],[currency]]="NGN", (Orders[[#This Row],[Unit Price]]*Orders[[#This Row],[Quantity]]/Details!$M$6), (Orders[[#This Row],[Unit Price]]*Orders[[#This Row],[Quantity]]/Details!$M$5)) -> 29.850746
A5: 44378.18 | B5: Mrs Omolara | C5: Kiosk | D5: Unilever Nigeria Plc | E5: Lipton Special | F5: Breakfast & Snacks | G5: 9 | H5: 3500 | I5: delivered | J5: Idris Habib Adewale | K5: Lagos | L5: NG | M5: NGN | N5: Telesales | O5: =IF(Orders[[#This Row],[currency]]="NGN", (Orders[[#This Row],[Unit Price]]*Orders[[#This Row],[Quantity]]/Details!$M$6), (Orders[[#This Row],[Unit Price]]*Orders[[#This Row],[Quantity]]/Details!$M$5)) -> 78.358209
A6: 44378.268 | B6: Adeyemi Stores | C6: Convenience Store | D6: Unilever Nigeria Plc | E6: Lipton Special | F6: Breakfast & Snacks | G6: 10 | H6: 3500 | I6: delivered | J6: Deji Ibironke | K6: Lagos | L6: NG | M6: NGN | N6: Field Sales | O6: =IF(Orders[[#This Row],[currency]]="NGN", (Orders[[#This Row],[Unit Price]]*Orders[[#This Row],[Quantity]]/Details!$M$6), (Orders[[#This Row],[Unit Price]]*Orders[[#This Row],[Quantity]]/Details!$M$5)) -> 87.064677
A7: 44378.276 | B7: Adeez Store | C7: Convenience Store | D7: Unilever Nigeria Plc | E7: Lipton Special | F7: Breakfast & Snacks | G7: 10 | H7: 3500 | I7: delivered | J7: Bolaji Olasunkanmi | K7: Lagos | L7: NG | M7: NGN | N7: Field Sales | O7: =IF(Orders[[#This Row],[currency]]="NGN", (Orders[[#This Row],[Unit Price]]*Orders[[#This Row],[Quantity]]/Details!$M$6), (Orders[[#This Row],[Unit Price]]*Orders[[#This Row],[Quantity]]/Details!$M$5)) -> 87.064677
A8: 44378.281 | B8: Kfm Olayiwola Ventures | C8: Supermarket | D8: Unilever Nigeria Plc | E8: Lipton Special | F8: Breakfast & Snacks | G8: 20 | H8: 3500 | I8: delivered | J8: Adewale Mustapha | K8: Lagos | L8: NG | M8: NGN | N8: Field Sales | O8: =IF(Orders[[#This Row],[currency]]="NGN", (Orders[[#This Row],[Unit Price]]*Orders[[#This Row],[Quantity]]/Details!$M$6), (Orders[[#This Row],[Unit Price]]*Orders[[#This Row],[Quantity]]/Details!$M$5)) -> 174.12935
A9: 44378.285 | B9: Ajoseph Store | C9: Convenience Store | D9: Unilever Nigeria Plc | E9: Close up | F9: Personal Care | G9: 50 | H9: 4900 | I9: delivered | J9: Adewale Mustapha | K9: Lagos | L9: NG | M9: NGN | N9: Field Sales | O9: =IF(Orders[[#This Row],[currency]]="NGN", (Orders[[#This Row],[Unit Price]]*Orders[[#This Row],[Quantity]]/Details!$M$6), (Orders[[#This Row],[Unit Price]]*Orders[[#This Row],[Quantity]]/Details!$M$5)) -> 609.45274
A10: 44378.293 | B10: Sebenzisa Tuck Shop | C10: Convenience Store | D10: Unilever SA | E10: Sunlight Dishwashing Liquid | F10: Home Care | G10: 1 | H10: 83.63 | I10: delivered | J10: Ismael Ishmael | K10: Gauteng | L10: ZA | M10: ZAR | N10: Mobile App | O10: =IF(Orders[[#This Row],[currency]]="NGN", (Orders[[#This Row],[Unit Price]]*Orders[[#This Row],[Quantity]]/Details!$M$6), (Orders[[#This Row],[Unit Price]]*Orders[[#This Row],[Quantity]]/Details!$M$5)) -> 5.6813859
A11: 44378.294 | B11: Iya Solo Alaba | C11: Kiosk | D11: Unilever Nigeria Plc | E11: Lipton Special | F11: Breakfast & Snacks | G11: 20 | H11: 3500 | I11: delivered | J11: Olanrewaju Dare Emmanuel | K11: Lagos | L11: NG | M11: NGN | N11: Field Sales | O11: =IF(Orders[[#This Row],[currency]]="NGN", (Orders[[#This Row],[Unit Price]]*Orders[[#This Row],[Quantity]]/Details!$M$6), (Orders[[#This Row],[Unit Price]]*Orders[[#This Row],[Quantity]]/Details!$M$5)) -> 174.12935
A12: 44378.302 | B12: Charley Stores | C12: Supermarket | D12: Extreme Manufacturing Nig Ltd | E12: Indomie Super Pack | F12: Food | G12: 100 | H12: 2500 | I12: delivered | J12: Saheed Olugbenga-Rufus | K12: Lagos | L12: NG | M12: NGN | N12: Field Sales | O12: =IF(Orders[[#This Row],[currency]]="NGN", (Orders[[#This Row],[Unit Price]]*Orders[[#This Row],[Quantity]]/Details!$M$6), (Orders[[#This Row],[Unit Price]]*Orders[[#This Row],[Quantity]]/Details!$M$5)) -> 621.89055
A13: 44378.31 | B13: Family Tuck Shop | C13: Supermarket | D13: Unilever SA | E13: Sunlight Dishwashing Liquid | F13: Home Care | G13: 1 | H13: 119.95 | I13: delivered | J13: Kagiso Katlego | K13: Gauteng | L13: ZA | M13: ZAR | N13: Mobile App | O13: =IF(Orders[[#This Row],[currency]]="NGN", (Orders[[#This Row],[Unit Price]]*Orders[[#This Row],[Quantity]]/Details!$M$6), (Orders[[#This Row],[Unit Price]]*Orders[[#This Row],[Quantity]]/Details!$M$5)) -> 8.1487772
... A8905: 44408.933 | B8905: Zimstores | C8905: Kiosk | D8905: Flour Mills of Nigeria | E8905: Golden Penny Spaghetti | F8905: Food | G8905: 3 | H8905: 5050 | I8905: delivered | J8905: Cole Olubunmi Adebowale | K8905: Lagos | L8905: NG | M8905: NGN | N8905: Mobile App | O8905: =IF(Orders[[#This Row],[currency]]="NGN", (Orders[[#This Row],[Unit Price]]*Orders[[#This Row],[Quantity]]/Details!$M$6), (Orders[[#This Row],[Unit Price]]*Orders[[#This Row],[Quantity]]/Details!$M$5)) -> 37.686567

Sheet DashBoard

Sheet Project
A1: Project Questions
A2: 1. create a chart to show the 10 least loyal customers
A3: 2. What percentage of sales come from each outlet type
A4: 3. What producers account for the 5 lowest sales figure
A5: 4. Averae order quantity per category group
A6: 5. make a chart showing the shipping status by outlet type
A7: 6. show the 10 worst perfroming delivery agents
A8: 7. most popular states by sales channel
A9: 8. 10 VIP customers
A10: 9. percentage of sales volume by sales channel and country
A12: NOTE: You need to derive a column that shows the sales figure.
A13: The unit price column is in naira (NGN) and south african rand (ZAR), depending on the country the sales was made. You might need to convert to dollars as all analysis should be in dollars
... A18: Order quantity between 301-1000 falls under 'High End' orders

Sheet Answer 1
A2: Row Labels | B2: Sum of Column1
A3: Busy Corner Supermarket | B3: 2.59375
A4: Cost Price | B4: 3.8716033
A5: Face To Face | B5: 0.40743886
A6: Mummy Tboy Store | B6: 2.7363184
A7: Sb | B7: 3.8247283
A8: Takas Grocery | B8: 2.65625
A9: Tina Shop | B9: 2.7363184
A10: Tina Store | B10: 2.7363184
A11: Tomitope Stores | B11: 2.7363184
A12: (blank)
A13: Grand Total | B13: 24.299044

Sheet Answer 2
A3: Row Labels | B3: Sum of Column1
A4: Convenience Store | B4: 151064.54
A5: Kiosk | B5: 116022.19
A6: Supermarket | B6: 117639.76
A7: Grand Total | B7: 384726.48

Sheet Answer 3
A3: Producer | B3: Sum of Column1
A4: Danone Nigeria | B4: 6607.6363
A5: Extreme Manufacturing Nig Ltd | B5: 7613.9303
A6: Nasco | B6: 5498.7811
A7: Nourdm Global | B7: 2136.0697
A8: (blank)
A9: Grand Total | B9: 21856.417

Sheet Answer 4
A3: Category Group | B3: Average of Quantity
A4: Baby | B4: 2.2989324
A5: Breakfast & Snacks | B5: 5.6121495
A6: Drinks | B6: 17.570552
A7: Food | B7: 5.0047911
A8: Home Care | B8: 2.6395062
A9: Personal Care | B9: 1.358804
A10: Wine & Spirits | B10: 2.85
A11: Grand Total | B11: 4.1458895

Sheet Answer 5
A3: Sum of Quantity | B3: Column Labels
A4: Row Labels | B4: cancelled | C4: delivered | D4: Grand Total
A5: Convenience Store | B5: 565 | C5: 13809.5 | D5: 14374.5
A6: Kiosk | B6: 567 | C6: 10690.25 | D6: 11257.25
A7: Supermarket | B7: 650 | C7: 10633.25 | D7: 11283.25
A8: Grand Total | B8: 1782 | C8: 35133 | D8: 36915

Sheet Answer 6
A3: Row Labels | B3: Sum of Column1
A4: Adetoro Oluranti | B4: 95.995025
A5: Agenu Chukwudi | B5: 122.63682
A6: Akinwande Akinbiyi | B6: 50.28607
A7: Asor Henry | B7: 162.48756
A8: Azeez Sahad | B8: 164.05473
A9: Clement Adeshina | B9: 263.0597
A10: Ekemenah Eduvie Steve | B10: 187.36318
A11: Kingsley Okore Kalu | B11: 56.467662
A12: Olaleye Thomas | B12: 104.47761
A13: (blank)
A14: Grand Total | B14: 1206.8284

Sheet Answer 7
A3: Sum of Column1 | B3: Column Labels
A4: Row Labels | B4: Field Sales | C4: Mobile App | D4: Telesales | E4: Grand Total
A5: Abia | B5: 2487.5622 | C5: 69.552239 | E5: 2557.1144
A6: Anambra | B6: 4344.5274 | E6: 4344.5274
A7: FCT | B7: 48079.502 | E7: 48079.502
A8: Gauteng | C8: 20474.661 | D8: 6550.0849 | E8: 27024.746
A9: Kano | B9: 9919.1542 | E9: 9919.1542
A10: Katlehong | C10: 27.686413 | E10: 27.686413
A11: Lagos | B11: 175217.53 | C11: 11401.219 | D11: 61161.48 | E11: 247780.23
A12: Ogun | B12: 29248.483 | C12: 1948.6194 | D12: 10507.761 | E12: 41704.863
A13: Oyo | B13: 1730.8458 | E13: 1730.8458
A14: Rivers | B14: 1534.8259 | E14: 1534.8259
A15: Soweto | C15: 22.97962 | E15: 22.97962
A16: Grand Total | B16: 272562.43 | C16: 33944.718 | D16: 78219.326 | E16: 384726.48

Sheet Answer 8
A4: Row Labels | B4: Sum of Column1
A5: Ym Stores | B5: 4968.9055
A6: Royal Born Store Lagos State | B6: 6843.4701
A7: Oreofe Stores | B7: 4424.1294
A8: Nonye Store | B8: 5184.602
A9: Iya Ruka K Store | B9: 7657.1642
A10: Green Leaves General Enterprise | B10: 4959.5771
A11: Gidan Sama Supermarket | B11: 5684.0796
A12: Benijraat Store | B12: 4610.8209
A13: Ben Green Venture Store | B13: 6886.2189
A14: Ail. Yusuf Lawan Usman, Provision And Cosmetics | B14: 4959.5771

Sheet Answer 9
A3: Count of salesChannel | B3: Column Labels
A4: Row Labels | B4: Field Sales | C4: Mobile App | D4: Telesales | E4: (blank) | F4: Grand Total
A5: NG | B5: 0.16172507 | C5: 0.055592992 | D5: 0.27044025 | E5: 0 | F5: 0.48775831
A6: ZA | B6: 0 | C6: 0.4034142 | D6: 0.10882749 | E6: 0 | F6: 0.51224169
A7: (blank) | B7: 0 | C7: 0 | D7: 0 | E7: 0 | F7: 0
A8: Grand Total | B8: 0.16172507 | C8: 0.45900719 | D8: 0.37926774 | E8: 0 | F8: 1
